LICENSE.txt
MANIFEST.in
README.rst
setup.cfg
setup.py
pymobius/__init__.py
pymobius/mobius.py
pymobius/requestor.py
pymobius.egg-info/PKG-INFO
pymobius.egg-info/SOURCES.txt
pymobius.egg-info/dependency_links.txt
pymobius.egg-info/not-zip-safe
pymobius.egg-info/requires.txt
pymobius.egg-info/top_level.txt
pymobius/abstract/__init__.py
pymobius/abstract/resource.py
pymobius/resources/__init__.py
pymobius/resources/app_store.py
pymobius/resources/tokens.py