Metadata-Version: 1.2
Name: pymobius
Version: 1.0.1
Summary: Mobius Python API Client
Home-page: https://github.com/mobius-network/mobius-python
Author: mobius-network
Author-email: support@mobius.network
License: MIT
Keywords: mobius,api
Platform: UNKNOWN
Classifier: Development Status :: 5 - Production/Stable
Classifier: License :: OSI Approved :: MIT License
Classifier: Programming Language :: Python :: 3.2
Classifier: Programming Language :: Python :: 3.3
Classifier: Programming Language :: Python :: 3.4
Classifier: Programming Language :: Python :: 3.5
Classifier: Programming Language :: Python :: 3.6
Requires-Python: >=3.2
